awslabs/__init__.py
awslabs/cost_analysis_mcp_server/__init__.py
awslabs/cost_analysis_mcp_server/cdk_analyzer.py
awslabs/cost_analysis_mcp_server/consts.py
awslabs/cost_analysis_mcp_server/helpers.py
awslabs/cost_analysis_mcp_server/pricing_client.py
awslabs/cost_analysis_mcp_server/report_generator.py
awslabs/cost_analysis_mcp_server/server.py
awslabs/cost_analysis_mcp_server/terraform_analyzer.py
awslabs/cost_analysis_mcp_server/static/__init__.py
awslabs/cost_analysis_mcp_server/static/patterns/__init__.py
mseep_awslabs_cost_analysis_mcp_server-1.0.3.dist-info/licenses/LICENSE
mseep_awslabs_cost_analysis_mcp_server-1.0.3.dist-info/licenses/NOTICE
tests/__init__.py
tests/conftest.py
tests/test_cdk_analyzer.py
tests/test_helpers.py
tests/test_pricing_client.py
tests/test_report_generator.py
tests/test_server.py
tests/test_terraform_analyzer.py
mseep_awslabs_cost_analysis_mcp_server-1.0.3.dist-info/METADATA
mseep_awslabs_cost_analysis_mcp_server-1.0.3.dist-info/WHEEL
mseep_awslabs_cost_analysis_mcp_server-1.0.3.dist-info/top_level.txt
mseep_awslabs_cost_analysis_mcp_server-1.0.3.dist-info/RECORD
