Metadata-Version: 2.4
Name: mseep-awslabs.cost-analysis-mcp-server
Version: 1.0.3
Summary: An AWS Labs Model Context Protocol (MCP) server for Cost Analysis of the AWS services
Home-page: https://github.com/mseep
Author: mseep
Author-email: support@skydeck.ai
Maintainer: mseep
Maintainer-email: support@skydeck.ai
Keywords: mseep
Classifier: Programming Language :: Python :: 3
Classifier: License :: OSI Approved :: MIT License
Classifier: Operating System :: OS Independent
Requires-Python: >=3.6
License-File: LICENSE
License-File: NOTICE
Requires-Dist: mcp[cli]>=1.6.0
Requires-Dist: pydantic>=2.10.6
Requires-Dist: boto3>=1.36.20
Requires-Dist: bs4>=0.0.2
Requires-Dist: pytest>=7.4.0
Requires-Dist: pytest-asyncio>=0.23.0
Requires-Dist: typing-extensions>=4.8.0
Requires-Dist: loguru>=0.7.3
Dynamic: author
Dynamic: author-email
Dynamic: classifier
Dynamic: description
Dynamic: description-content-type
Dynamic: home-page
Dynamic: keywords
Dynamic: license-file
Dynamic: maintainer
Dynamic: maintainer-email
Dynamic: requires-dist
Dynamic: requires-python
Dynamic: summary
